sphinxcontrib/devhelp/__init__.py
sphinxcontrib/devhelp/locales/sphinxcontrib.devhelp.pot
sphinxcontrib/devhelp/locales/.tx/config
sphinxcontrib/devhelp/locales/ar/LC_MESSAGES/sphinxcontrib.devhelp.mo
sphinxcontrib/devhelp/locales/ar/LC_MESSAGES/sphinxcontrib.devhelp.po
sphinxcontrib/devhelp/locales/bn/LC_MESSAGES/sphinxcontrib.devhelp.mo
sphinxcontrib/devhelp/locales/bn/LC_MESSAGES/sphinxcontrib.devhelp.po
sphinxcontrib/devhelp/locales/ca/LC_MESSAGES/sphinxcontrib.devhelp.mo
sphinxcontrib/devhelp/locales/ca/LC_MESSAGES/sphinxcontrib.devhelp.po
sphinxcontrib/devhelp/locales/cs/LC_MESSAGES/sphinxcontrib.devhelp.mo
sphinxcontrib/devhelp/locales/cs/LC_MESSAGES/sphinxcontrib.devhelp.po
sphinxcontrib/devhelp/locales/cy/LC_MESSAGES/sphinxcontrib.devhelp.mo
sphinxcontrib/devhelp/locales/cy/LC_MESSAGES/sphinxcontrib.devhelp.po
sphinxcontrib/devhelp/locales/da/LC_MESSAGES/sphinxcontrib.devhelp.mo
sphinxcontrib/devhelp/locales/da/LC_MESSAGES/sphinxcontrib.devhelp.po
sphinxcontrib/devhelp/locales/de/LC_MESSAGES/sphinxcontrib.devhelp.mo
sphinxcontrib/devhelp/locales/de/LC_MESSAGES/sphinxcontrib.devhelp.po
sphinxcontrib/devhelp/locales/el/LC_MESSAGES/sphinxcontrib.devhelp.mo
sphinxcontrib/devhelp/locales/el/LC_MESSAGES/sphinxcontrib.devhelp.po
sphinxcontrib/devhelp/locales/eo/LC_MESSAGES/sphinxcontrib.devhelp.mo
sphinxcontrib/devhelp/locales/eo/LC_MESSAGES/sphinxcontrib.devhelp.po
sphinxcontrib/devhelp/locales/es/LC_MESSAGES/sphinxcontrib.devhelp.mo
sphinxcontrib/devhelp/locales/es/LC_MESSAGES/sphinxcontrib.devhelp.po
sphinxcontrib/devhelp/locales/et/LC_MESSAGES/sphinxcontrib.devhelp.mo
sphinxcontrib/devhelp/locales/et/LC_MESSAGES/sphinxcontrib.devhelp.po
sphinxcontrib/devhelp/locales/eu/LC_MESSAGES/sphinxcontrib.devhelp.mo
sphinxcontrib/devhelp/locales/eu/LC_MESSAGES/sphinxcontrib.devhelp.po
sphinxcontrib/devhelp/locales/fa/LC_MESSAGES/sphinxcontrib.devhelp.mo
sphinxcontrib/devhelp/locales/fa/LC_MESSAGES/sphinxcontrib.devhelp.po
sphinxcontrib_devhelp-1.0.3.dist-info/LICENSE
sphinxcontrib_devhelp-1.0.3.dist-info/WHEEL
sphinxcontrib_devhelp-1.0.3.dist-info/METADATA
sphinxcontrib_devhelp-1.0.3.dist-info/RECORD
